LICENSE.md
README.md
pyproject.toml
src/llmflex/__init__.py
src/llmflex/cli.py
src/llmflex/utils.py
src/llmflex.egg-info/PKG-INFO
src/llmflex.egg-info/SOURCES.txt
src/llmflex.egg-info/dependency_links.txt
src/llmflex.egg-info/entry_points.txt
src/llmflex.egg-info/requires.txt
src/llmflex.egg-info/top_level.txt
src/llmflex/Agents/__init__.py
src/llmflex/Agents/base_agent.py
src/llmflex/Embeddings/__init__.py
src/llmflex/Embeddings/api_embeddings.py
src/llmflex/Embeddings/base_embeddings.py
src/llmflex/Embeddings/hf_embeddings_server.py
src/llmflex/Embeddings/huggingface_embeddings.py
src/llmflex/Frontend/__init__.py
src/llmflex/Frontend/app_resource.py
src/llmflex/Frontend/streamlit_interface.py
src/llmflex/KnowledgeBase/__init__.py
src/llmflex/KnowledgeBase/knowledge_base.py
src/llmflex/Memory/__init__.py
src/llmflex/Memory/base_memory.py
src/llmflex/Memory/long_short_memory.py
src/llmflex/Memory/memory_utils.py
src/llmflex/Models/__init__.py
src/llmflex/Models/Cores/__init__.py
src/llmflex/Models/Cores/base_core.py
src/llmflex/Models/Cores/exllamav2_core.py
src/llmflex/Models/Cores/huggingface_core.py
src/llmflex/Models/Cores/llamacpp_core.py
src/llmflex/Models/Cores/openai_core.py
src/llmflex/Models/Cores/utils.py
src/llmflex/Models/Factory/__init__.py
src/llmflex/Models/Factory/llm_factory.py
src/llmflex/Prompts/__init__.py
src/llmflex/Prompts/prompt_template.py
src/llmflex/Rankers/__init__.py
src/llmflex/Rankers/base_ranker.py
src/llmflex/Rankers/flashrank_ranker.py
src/llmflex/Schemas/__init__.py
src/llmflex/Schemas/documents.py
src/llmflex/Schemas/tokenizer.py
src/llmflex/TextSplitters/__init__.py
src/llmflex/TextSplitters/base_text_splitter.py
src/llmflex/TextSplitters/sentence_token_text_splitter.py
src/llmflex/TextSplitters/token_text_splitter.py
src/llmflex/Tools/__init__.py
src/llmflex/Tools/browser_tool.py
src/llmflex/Tools/sd_tool.py
src/llmflex/Tools/tool_classes.py
src/llmflex/Tools/tool_utils.py
src/llmflex/Tools/web_search_utils.py
src/llmflex/VectorDBs/__init__.py
src/llmflex/VectorDBs/base_vectordb.py
src/llmflex/VectorDBs/faiss_vectordb.py