Metadata-Version: 2.1
Name: llmflex
Version: 0.1.11
Summary: A python package for developing AI applications with local LLMs.
Author-email: Nathan Tam <nathan1295@gmail.com>
License: MIT
Project-URL: Homepage, https://github.com/nath1295/LLMFlex
Requires-Python: >=3.9
License-File: LICENSE.md
Requires-Dist: click
Requires-Dist: torch
Requires-Dist: llama-cpp-python
Requires-Dist: transformers>=4.35.0
Requires-Dist: accelerate>=0.25.0
Requires-Dist: sentence-transformers
Requires-Dist: langchain
Requires-Dist: faiss-cpu
Requires-Dist: optimum
Requires-Dist: gradio>=4.2
Requires-Dist: duckduckgo-search>=6.1.0
Requires-Dist: fake-useragent
Requires-Dist: openai>=1.0.0
Requires-Dist: tiktoken
Requires-Dist: protobuf
Requires-Dist: beautifulsoup4
Requires-Dist: streamlit
Requires-Dist: streamlit-extras
Requires-Dist: watchdog
Requires-Dist: guidance
Requires-Dist: spacy>=3.7.0
Requires-Dist: flask
Requires-Dist: PyMuPDF
Requires-Dist: flashrank
Requires-Dist: python-docx
Provides-Extra: cu121
Requires-Dist: auto-gptq>=0.6.0; extra == "cu121"
Requires-Dist: autoawq; extra == "cu121"
Requires-Dist: exllamav2; extra == "cu121"
Provides-Extra: cu118
Requires-Dist: auto-gptq; extra == "cu118"
Requires-Dist: autoawq; extra == "cu118"
Requires-Dist: exllamav2; extra == "cu118"
